MANIFEST.in
README.rst
example.cfg
setup.py
plutopluto/__init__.py
plutopluto/index.html
plutopluto.egg-info/PKG-INFO
plutopluto.egg-info/SOURCES.txt
plutopluto.egg-info/dependency_links.txt
plutopluto.egg-info/entry_points.txt
plutopluto.egg-info/requires.txt
plutopluto.egg-info/top_level.txt
plutopluto/static/color.css
plutopluto/static/favicon.ico
plutopluto/static/jqlite.js
plutopluto/static/mustache.js
plutopluto/static/plutopluto.css
plutopluto/static/plutopluto.js