Metadata-Version: 1.1
Name: plutopluto
Version: 1.2.0
Summary: simple feed aggregator
Home-page: https://github.com/xi/plutopluto
Author: Tobias Bengfort
Author-email: tobias.bengfort@posteo.de
License: GPLv2+
Platform: UNKNOWN
Classifier: Environment :: Web Environment
Classifier: Intended Audience :: End Users/Desktop
Classifier: Operating System :: OS Independent
Classifier: Programming Language :: Python
Classifier: Programming Language :: JavaScript
Classifier: License :: OSI Approved :: GNU General Public License v2 or later (GPLv2+)
Classifier: Topic :: Internet :: WWW/HTTP :: Dynamic Content :: News/Diary
